<?xml version="1.0" encoding="UTF-8" standalone="no"?>
<room id="485">
  <caption>[G5-4M] From that point, we really felt like a team, rather than a collection of random people playing Zephyr's game.</caption>
  <size height="448" width="608"/>
  <grid>
    <isometric>false</isometric>
    <snap x="16" y="16"/>
  </grid>
  <speed>30</speed>
  <persistent>false</persistent>
  <creationCode>locationCheck(49)

gameScene=instance_create(0,0,oEvCh13MainA)
metroidControl=instance_create(0,0,oEvCh13MetroidControl)

global.currentBoss=""
global.bossTrack=0

var tempMplay;
tempMplay=findMusic(505)
playMusic(tempMplay,0,0)</creationCode>
  <backgroundColor>400000</backgroundColor>
  <drawBackgroundColor>true</drawBackgroundColor>
  <clearViewBackground>true</clearViewBackground>
  <backgrounds>
    <backgroundDef>
      <visibleOnRoomStart>true</visibleOnRoomStart>
      <isForeground>false</isForeground>
      <backgroundImage>backMetF1</backgroundImage>
      <offset x="0" y="0"/>
      <speed x="0" y="0"/>
      <tileHorizontally>true</tileHorizontally>
      <tileVertically>true</tileVertically>
      <stretch>false</stretch>
    </backgroundDef>
    <backgroundDef>
      <visibleOnRoomStart>false</visibleOnRoomStart>
      <isForeground>false</isForeground>
      <backgroundImage/>
      <offset x="0" y="0"/>
      <speed x="0" y="0"/>
      <tileHorizontally>true</tileHorizontally>
      <tileVertically>true</tileVertically>
      <stretch>false</stretch>
    </backgroundDef>
    <backgroundDef>
      <visibleOnRoomStart>false</visibleOnRoomStart>
      <isForeground>false</isForeground>
      <backgroundImage/>
      <offset x="0" y="0"/>
      <speed x="0" y="0"/>
      <tileHorizontally>true</tileHorizontally>
      <tileVertically>true</tileVertically>
      <stretch>false</stretch>
    </backgroundDef>
    <backgroundDef>
      <visibleOnRoomStart>false</visibleOnRoomStart>
      <isForeground>false</isForeground>
      <backgroundImage/>
      <offset x="0" y="0"/>
      <speed x="0" y="0"/>
      <tileHorizontally>true</tileHorizontally>
      <tileVertically>true</tileVertically>
      <stretch>false</stretch>
    </backgroundDef>
    <backgroundDef>
      <visibleOnRoomStart>false</visibleOnRoomStart>
      <isForeground>false</isForeground>
      <backgroundImage/>
      <offset x="0" y="0"/>
      <speed x="0" y="0"/>
      <tileHorizontally>true</tileHorizontally>
      <tileVertically>true</tileVertically>
      <stretch>false</stretch>
    </backgroundDef>
    <backgroundDef>
      <visibleOnRoomStart>false</visibleOnRoomStart>
      <isForeground>false</isForeground>
      <backgroundImage/>
      <offset x="0" y="0"/>
      <speed x="0" y="0"/>
      <tileHorizontally>true</tileHorizontally>
      <tileVertically>true</tileVertically>
      <stretch>false</stretch>
    </backgroundDef>
    <backgroundDef>
      <visibleOnRoomStart>false</visibleOnRoomStart>
      <isForeground>false</isForeground>
      <backgroundImage/>
      <offset x="0" y="0"/>
      <speed x="0" y="0"/>
      <tileHorizontally>true</tileHorizontally>
      <tileVertically>true</tileVertically>
      <stretch>false</stretch>
    </backgroundDef>
    <backgroundDef>
      <visibleOnRoomStart>false</visibleOnRoomStart>
      <isForeground>false</isForeground>
      <backgroundImage/>
      <offset x="0" y="0"/>
      <speed x="0" y="0"/>
      <tileHorizontally>true</tileHorizontally>
      <tileVertically>true</tileVertically>
      <stretch>false</stretch>
    </backgroundDef>
  </backgrounds>
  <enableViews>true</enableViews>
  <views>
    <view>
      <visibleOnRoomStart>true</visibleOnRoomStart>
      <viewInRoom height="352" width="480" x="0" y="0"/>
      <portOnScreen height="352" width="480" x="0" y="0"/>
      <objectFollowing hBorder="240" hSpeed="-1" vBorder="176" vSpeed="-1">oPlayer1</objectFollowing>
    </view>
    <view>
      <visibleOnRoomStart>false</visibleOnRoomStart>
      <viewInRoom height="480" width="640" x="0" y="0"/>
      <portOnScreen height="480" width="640" x="0" y="0"/>
      <objectFollowing hBorder="32" hSpeed="-1" vBorder="32" vSpeed="-1"/>
    </view>
    <view>
      <visibleOnRoomStart>false</visibleOnRoomStart>
      <viewInRoom height="480" width="640" x="0" y="0"/>
      <portOnScreen height="480" width="640" x="0" y="0"/>
      <objectFollowing hBorder="32" hSpeed="-1" vBorder="32" vSpeed="-1"/>
    </view>
    <view>
      <visibleOnRoomStart>false</visibleOnRoomStart>
      <viewInRoom height="480" width="640" x="0" y="0"/>
      <portOnScreen height="480" width="640" x="0" y="0"/>
      <objectFollowing hBorder="32" hSpeed="-1" vBorder="32" vSpeed="-1"/>
    </view>
    <view>
      <visibleOnRoomStart>false</visibleOnRoomStart>
      <viewInRoom height="480" width="640" x="0" y="0"/>
      <portOnScreen height="480" width="640" x="0" y="0"/>
      <objectFollowing hBorder="32" hSpeed="-1" vBorder="32" vSpeed="-1"/>
    </view>
    <view>
      <visibleOnRoomStart>false</visibleOnRoomStart>
      <viewInRoom height="480" width="640" x="0" y="0"/>
      <portOnScreen height="480" width="640" x="0" y="0"/>
      <objectFollowing hBorder="32" hSpeed="-1" vBorder="32" vSpeed="-1"/>
    </view>
    <view>
      <visibleOnRoomStart>false</visibleOnRoomStart>
      <viewInRoom height="480" width="640" x="0" y="0"/>
      <portOnScreen height="480" width="640" x="0" y="0"/>
      <objectFollowing hBorder="32" hSpeed="-1" vBorder="32" vSpeed="-1"/>
    </view>
    <view>
      <visibleOnRoomStart>false</visibleOnRoomStart>
      <viewInRoom height="480" width="640" x="0" y="0"/>
      <portOnScreen height="480" width="640" x="0" y="0"/>
      <objectFollowing hBorder="32" hSpeed="-1" vBorder="32" vSpeed="-1"/>
    </view>
  </views>
  <instances>
    <instance id="295556">
      <object>oExit</object>
      <position x="592" y="336"/>
      <creationCode>bShowArrow=false
exitType=1
newMapX=64
newMapY=128
toRoom=rSamus5_Lv4_L</creationCode>
      <locked>false</locked>
    </instance>
    <instance id="295777">
      <object>oExit</object>
      <position x="0" y="336"/>
      <creationCode>bShowArrow=false
exitType=1
newMapX=416
newMapY=272
toRoom=rSamus5_Lv4_N</creationCode>
      <locked>false</locked>
    </instance>
    <instance id="295557">
      <object>oPlayer1</object>
      <position x="544" y="368"/>
      <creationCode/>
      <locked>false</locked>
    </instance>
    <instance id="295553">
      <object>oMetroidDoorHolder</object>
      <position x="576" y="336"/>
      <creationCode>image_angle=180
type=0</creationCode>
      <locked>false</locked>
    </instance>
    <instance id="295554">
      <object>oMetroidDoorHolder</object>
      <position x="16" y="336"/>
      <creationCode>type=0</creationCode>
      <locked>false</locked>
    </instance>
    <instance id="295725">
      <object>oMetLava</object>
      <position x="256" y="384"/>
      <creationCode>image_xscale=6
image_yscale=3
scaling=16
image_blend=c_purple</creationCode>
      <locked>false</locked>
    </instance>
    <instance id="295562">
      <object>oInvCollPH</object>
      <position x="48" y="32"/>
      <creationCode/>
      <locked>false</locked>
    </instance>
    <instance id="295563">
      <object>oInvCollPH</object>
      <position x="48" y="48"/>
      <creationCode/>
      <locked>false</locked>
    </instance>
    <instance id="295564">
      <object>oInvCollPH</object>
      <position x="48" y="64"/>
      <creationCode/>
      <locked>false</locked>
    </instance>
    <instance id="295565">
      <object>oInvCollPH</object>
      <position x="48" y="80"/>
      <creationCode/>
      <locked>false</locked>
    </instance>
    <instance id="295566">
      <object>oInvCollPH</object>
      <position x="48" y="96"/>
      <creationCode/>
      <locked>false</locked>
    </instance>
    <instance id="295567">
      <object>oInvCollPH</object>
      <position x="48" y="112"/>
      <creationCode/>
      <locked>false</locked>
    </instance>
    <instance id="295568">
      <object>oInvCollPH</object>
      <position x="48" y="128"/>
      <creationCode/>
      <locked>false</locked>
    </instance>
    <instance id="295569">
      <object>oInvCollPH</object>
      <position x="48" y="144"/>
      <creationCode/>
      <locked>false</locked>
    </instance>
    <instance id="295570">
      <object>oInvCollPH</object>
      <position x="48" y="160"/>
      <creationCode/>
      <locked>false</locked>
    </instance>
    <instance id="295571">
      <object>oInvCollPH</object>
      <position x="48" y="176"/>
      <creationCode/>
      <locked>false</locked>
    </instance>
    <instance id="295572">
      <object>oInvCollPH</object>
      <position x="0" y="288"/>
      <creationCode/>
      <locked>false</locked>
    </instance>
    <instance id="295573">
      <object>oInvCollPH</object>
      <position x="16" y="288"/>
      <creationCode/>
      <locked>false</locked>
    </instance>
    <instance id="295574">
      <object>oInvCollPH</object>
      <position x="32" y="288"/>
      <creationCode/>
      <locked>false</locked>
    </instance>
    <instance id="295577">
      <object>oInvCollPH</object>
      <position x="48" y="288"/>
      <creationCode/>
      <locked>false</locked>
    </instance>
    <instance id="295578">
      <object>oInvCollPH</object>
      <position x="48" y="272"/>
      <creationCode/>
      <locked>false</locked>
    </instance>
    <instance id="295579">
      <object>oInvCollPH</object>
      <position x="48" y="256"/>
      <creationCode/>
      <locked>false</locked>
    </instance>
    <instance id="295580">
      <object>oInvCollPH</object>
      <position x="48" y="240"/>
      <creationCode/>
      <locked>false</locked>
    </instance>
    <instance id="295581">
      <object>oInvCollPH</object>
      <position x="48" y="224"/>
      <creationCode/>
      <locked>false</locked>
    </instance>
    <instance id="295582">
      <object>oInvCollPH</object>
      <position x="48" y="208"/>
      <creationCode/>
      <locked>false</locked>
    </instance>
    <instance id="295583">
      <object>oInvCollPH</object>
      <position x="48" y="192"/>
      <creationCode/>
      <locked>false</locked>
    </instance>
    <instance id="295584">
      <object>oInvCollPH</object>
      <position x="544" y="48"/>
      <creationCode/>
      <locked>false</locked>
    </instance>
    <instance id="295585">
      <object>oInvCollPH</object>
      <position x="544" y="64"/>
      <creationCode/>
      <locked>false</locked>
    </instance>
    <instance id="295586">
      <object>oInvCollPH</object>
      <position x="544" y="80"/>
      <creationCode/>
      <locked>false</locked>
    </instance>
    <instance id="295587">
      <object>oInvCollPH</object>
      <position x="544" y="96"/>
      <creationCode/>
      <locked>false</locked>
    </instance>
    <instance id="295588">
      <object>oInvCollPH</object>
      <position x="544" y="112"/>
      <creationCode/>
      <locked>false</locked>
    </instance>
    <instance id="295589">
      <object>oInvCollPH</object>
      <position x="544" y="128"/>
      <creationCode/>
      <locked>false</locked>
    </instance>
    <instance id="295590">
      <object>oInvCollPH</object>
      <position x="544" y="144"/>
      <creationCode/>
      <locked>false</locked>
    </instance>
    <instance id="295591">
      <object>oInvCollPH</object>
      <position x="544" y="160"/>
      <creationCode/>
      <locked>false</locked>
    </instance>
    <instance id="295592">
      <object>oInvCollPH</object>
      <position x="544" y="176"/>
      <creationCode/>
      <locked>false</locked>
    </instance>
    <instance id="295593">
      <object>oInvCollPH</object>
      <position x="544" y="192"/>
      <creationCode/>
      <locked>false</locked>
    </instance>
    <instance id="295594">
      <object>oInvCollPH</object>
      <position x="544" y="208"/>
      <creationCode/>
      <locked>false</locked>
    </instance>
    <instance id="295595">
      <object>oInvCollPH</object>
      <position x="544" y="224"/>
      <creationCode/>
      <locked>false</locked>
    </instance>
    <instance id="295596">
      <object>oInvCollPH</object>
      <position x="544" y="240"/>
      <creationCode/>
      <locked>false</locked>
    </instance>
    <instance id="295597">
      <object>oInvCollPH</object>
      <position x="544" y="256"/>
      <creationCode/>
      <locked>false</locked>
    </instance>
    <instance id="295598">
      <object>oInvCollPH</object>
      <position x="544" y="272"/>
      <creationCode/>
      <locked>false</locked>
    </instance>
    <instance id="295599">
      <object>oInvCollPH</object>
      <position x="544" y="288"/>
      <creationCode/>
      <locked>false</locked>
    </instance>
    <instance id="295602">
      <object>oInvCollPH</object>
      <position x="560" y="288"/>
      <creationCode/>
      <locked>false</locked>
    </instance>
    <instance id="295603">
      <object>oInvCollPH</object>
      <position x="576" y="288"/>
      <creationCode/>
      <locked>false</locked>
    </instance>
    <instance id="295604">
      <object>oInvCollPH</object>
      <position x="592" y="288"/>
      <creationCode/>
      <locked>false</locked>
    </instance>
    <instance id="295605">
      <object>oInvCollPH</object>
      <position x="64" y="16"/>
      <creationCode/>
      <locked>false</locked>
    </instance>
    <instance id="295606">
      <object>oInvCollPH</object>
      <position x="80" y="16"/>
      <creationCode/>
      <locked>false</locked>
    </instance>
    <instance id="295607">
      <object>oInvCollPH</object>
      <position x="96" y="16"/>
      <creationCode/>
      <locked>false</locked>
    </instance>
    <instance id="295608">
      <object>oInvCollPH</object>
      <position x="112" y="16"/>
      <creationCode/>
      <locked>false</locked>
    </instance>
    <instance id="295609">
      <object>oInvCollPH</object>
      <position x="128" y="16"/>
      <creationCode/>
      <locked>false</locked>
    </instance>
    <instance id="295610">
      <object>oInvCollPH</object>
      <position x="144" y="16"/>
      <creationCode/>
      <locked>false</locked>
    </instance>
    <instance id="295611">
      <object>oInvCollPH</object>
      <position x="160" y="16"/>
      <creationCode/>
      <locked>false</locked>
    </instance>
    <instance id="295612">
      <object>oInvCollPH</object>
      <position x="176" y="16"/>
      <creationCode/>
      <locked>false</locked>
    </instance>
    <instance id="295613">
      <object>oInvCollPH</object>
      <position x="192" y="16"/>
      <creationCode/>
      <locked>false</locked>
    </instance>
    <instance id="295614">
      <object>oInvCollPH</object>
      <position x="208" y="16"/>
      <creationCode/>
      <locked>false</locked>
    </instance>
    <instance id="295615">
      <object>oInvCollPH</object>
      <position x="224" y="16"/>
      <creationCode/>
      <locked>false</locked>
    </instance>
    <instance id="295616">
      <object>oInvCollPH</object>
      <position x="240" y="16"/>
      <creationCode/>
      <locked>false</locked>
    </instance>
    <instance id="295617">
      <object>oInvCollPH</object>
      <position x="256" y="16"/>
      <creationCode/>
      <locked>false</locked>
    </instance>
    <instance id="295618">
      <object>oInvCollPH</object>
      <position x="272" y="16"/>
      <creationCode/>
      <locked>false</locked>
    </instance>
    <instance id="295619">
      <object>oInvCollPH</object>
      <position x="288" y="16"/>
      <creationCode/>
      <locked>false</locked>
    </instance>
    <instance id="295620">
      <object>oInvCollPH</object>
      <position x="304" y="16"/>
      <creationCode/>
      <locked>false</locked>
    </instance>
    <instance id="295621">
      <object>oInvCollPH</object>
      <position x="320" y="16"/>
      <creationCode/>
      <locked>false</locked>
    </instance>
    <instance id="295622">
      <object>oInvCollPH</object>
      <position x="336" y="16"/>
      <creationCode/>
      <locked>false</locked>
    </instance>
    <instance id="295623">
      <object>oInvCollPH</object>
      <position x="352" y="16"/>
      <creationCode/>
      <locked>false</locked>
    </instance>
    <instance id="295624">
      <object>oInvCollPH</object>
      <position x="368" y="16"/>
      <creationCode/>
      <locked>false</locked>
    </instance>
    <instance id="295625">
      <object>oInvCollPH</object>
      <position x="384" y="16"/>
      <creationCode/>
      <locked>false</locked>
    </instance>
    <instance id="295626">
      <object>oInvCollPH</object>
      <position x="400" y="16"/>
      <creationCode/>
      <locked>false</locked>
    </instance>
    <instance id="295627">
      <object>oInvCollPH</object>
      <position x="416" y="16"/>
      <creationCode/>
      <locked>false</locked>
    </instance>
    <instance id="295628">
      <object>oInvCollPH</object>
      <position x="432" y="16"/>
      <creationCode/>
      <locked>false</locked>
    </instance>
    <instance id="295629">
      <object>oInvCollPH</object>
      <position x="448" y="16"/>
      <creationCode/>
      <locked>false</locked>
    </instance>
    <instance id="295630">
      <object>oInvCollPH</object>
      <position x="464" y="16"/>
      <creationCode/>
      <locked>false</locked>
    </instance>
    <instance id="295631">
      <object>oInvCollPH</object>
      <position x="480" y="16"/>
      <creationCode/>
      <locked>false</locked>
    </instance>
    <instance id="295632">
      <object>oInvCollPH</object>
      <position x="496" y="16"/>
      <creationCode/>
      <locked>false</locked>
    </instance>
    <instance id="295633">
      <object>oInvCollPH</object>
      <position x="512" y="16"/>
      <creationCode/>
      <locked>false</locked>
    </instance>
    <instance id="295634">
      <object>oInvCollPH</object>
      <position x="528" y="16"/>
      <creationCode/>
      <locked>false</locked>
    </instance>
    <instance id="295679">
      <object>oInvCollPH</object>
      <position x="144" y="144"/>
      <creationCode/>
      <locked>false</locked>
    </instance>
    <instance id="295680">
      <object>oInvCollPH</object>
      <position x="160" y="144"/>
      <creationCode/>
      <locked>false</locked>
    </instance>
    <instance id="295681">
      <object>oInvCollPH</object>
      <position x="176" y="144"/>
      <creationCode/>
      <locked>false</locked>
    </instance>
    <instance id="295682">
      <object>oInvCollPH</object>
      <position x="272" y="144"/>
      <creationCode/>
      <locked>false</locked>
    </instance>
    <instance id="295683">
      <object>oInvCollPH</object>
      <position x="272" y="160"/>
      <creationCode/>
      <locked>false</locked>
    </instance>
    <instance id="295684">
      <object>oInvCollPH</object>
      <position x="272" y="176"/>
      <creationCode/>
      <locked>false</locked>
    </instance>
    <instance id="295685">
      <object>oInvCollPH</object>
      <position x="272" y="128"/>
      <creationCode/>
      <locked>false</locked>
    </instance>
    <instance id="295686">
      <object>oInvCollPH</object>
      <position x="288" y="176"/>
      <creationCode/>
      <locked>false</locked>
    </instance>
    <instance id="295687">
      <object>oInvCollPH</object>
      <position x="304" y="176"/>
      <creationCode/>
      <locked>false</locked>
    </instance>
    <instance id="295688">
      <object>oInvCollPH</object>
      <position x="320" y="112"/>
      <creationCode/>
      <locked>false</locked>
    </instance>
    <instance id="295689">
      <object>oInvCollPH</object>
      <position x="320" y="176"/>
      <creationCode/>
      <locked>false</locked>
    </instance>
    <instance id="295690">
      <object>oInvCollPH</object>
      <position x="320" y="160"/>
      <creationCode/>
      <locked>false</locked>
    </instance>
    <instance id="295691">
      <object>oInvCollPH</object>
      <position x="320" y="144"/>
      <creationCode/>
      <locked>false</locked>
    </instance>
    <instance id="295692">
      <object>oInvCollPH</object>
      <position x="320" y="128"/>
      <creationCode/>
      <locked>false</locked>
    </instance>
    <instance id="295693">
      <object>oInvCollPH</object>
      <position x="304" y="112"/>
      <creationCode/>
      <locked>false</locked>
    </instance>
    <instance id="295694">
      <object>oInvCollPH</object>
      <position x="288" y="112"/>
      <creationCode/>
      <locked>false</locked>
    </instance>
    <instance id="295695">
      <object>oInvCollPH</object>
      <position x="432" y="144"/>
      <creationCode/>
      <locked>false</locked>
    </instance>
    <instance id="295696">
      <object>oInvCollPH</object>
      <position x="448" y="144"/>
      <creationCode/>
      <locked>false</locked>
    </instance>
    <instance id="295697">
      <object>oInvCollPH</object>
      <position x="464" y="144"/>
      <creationCode/>
      <locked>false</locked>
    </instance>
    <instance id="295698">
      <object>oInvCollPH</object>
      <position x="112" y="144"/>
      <creationCode/>
      <locked>false</locked>
    </instance>
    <instance id="295699">
      <object>oInvCollPH</object>
      <position x="112" y="160"/>
      <creationCode/>
      <locked>false</locked>
    </instance>
    <instance id="295700">
      <object>oInvCollPH</object>
      <position x="112" y="176"/>
      <creationCode/>
      <locked>false</locked>
    </instance>
    <instance id="295701">
      <object>oInvCollPH</object>
      <position x="112" y="128"/>
      <creationCode/>
      <locked>false</locked>
    </instance>
    <instance id="295702">
      <object>oInvCollPH</object>
      <position x="480" y="144"/>
      <creationCode/>
      <locked>false</locked>
    </instance>
    <instance id="295703">
      <object>oInvCollPH</object>
      <position x="480" y="160"/>
      <creationCode/>
      <locked>false</locked>
    </instance>
    <instance id="295704">
      <object>oInvCollPH</object>
      <position x="480" y="176"/>
      <creationCode/>
      <locked>false</locked>
    </instance>
    <instance id="295705">
      <object>oInvCollPH</object>
      <position x="480" y="128"/>
      <creationCode/>
      <locked>false</locked>
    </instance>
    <instance id="295706">
      <object>oInvCollPH</object>
      <position x="176" y="272"/>
      <creationCode/>
      <locked>false</locked>
    </instance>
    <instance id="295707">
      <object>oInvCollPH</object>
      <position x="192" y="272"/>
      <creationCode/>
      <locked>false</locked>
    </instance>
    <instance id="295708">
      <object>oInvCollPH</object>
      <position x="208" y="272"/>
      <creationCode/>
      <locked>false</locked>
    </instance>
    <instance id="295709">
      <object>oInvCollPH</object>
      <position x="224" y="272"/>
      <creationCode/>
      <locked>false</locked>
    </instance>
    <instance id="295710">
      <object>oInvCollPH</object>
      <position x="240" y="272"/>
      <creationCode/>
      <locked>false</locked>
    </instance>
    <instance id="295711">
      <object>oInvCollPH</object>
      <position x="368" y="272"/>
      <creationCode/>
      <locked>false</locked>
    </instance>
    <instance id="295712">
      <object>oInvCollPH</object>
      <position x="384" y="272"/>
      <creationCode/>
      <locked>false</locked>
    </instance>
    <instance id="295713">
      <object>oInvCollPH</object>
      <position x="400" y="272"/>
      <creationCode/>
      <locked>false</locked>
    </instance>
    <instance id="295714">
      <object>oInvCollPH</object>
      <position x="416" y="272"/>
      <creationCode/>
      <locked>false</locked>
    </instance>
    <instance id="295715">
      <object>oInvCollPH</object>
      <position x="432" y="272"/>
      <creationCode/>
      <locked>false</locked>
    </instance>
    <instance id="295728">
      <object>oInvCollPH</object>
      <position x="272" y="432"/>
      <creationCode/>
      <locked>false</locked>
    </instance>
    <instance id="295729">
      <object>oInvCollPH</object>
      <position x="288" y="432"/>
      <creationCode/>
      <locked>false</locked>
    </instance>
    <instance id="295730">
      <object>oInvCollPH</object>
      <position x="304" y="432"/>
      <creationCode/>
      <locked>false</locked>
    </instance>
    <instance id="295731">
      <object>oInvCollPH</object>
      <position x="320" y="432"/>
      <creationCode/>
      <locked>false</locked>
    </instance>
    <instance id="295732">
      <object>oInvCollPH</object>
      <position x="336" y="432"/>
      <creationCode/>
      <locked>false</locked>
    </instance>
    <instance id="295733">
      <object>oInvCollPH</object>
      <position x="16" y="368"/>
      <creationCode/>
      <locked>false</locked>
    </instance>
    <instance id="295734">
      <object>oInvCollPH</object>
      <position x="32" y="368"/>
      <creationCode/>
      <locked>false</locked>
    </instance>
    <instance id="295735">
      <object>oInvCollPH</object>
      <position x="48" y="368"/>
      <creationCode/>
      <locked>false</locked>
    </instance>
    <instance id="295736">
      <object>oInvCollPH</object>
      <position x="64" y="368"/>
      <creationCode/>
      <locked>false</locked>
    </instance>
    <instance id="295737">
      <object>oInvCollPH</object>
      <position x="144" y="368"/>
      <creationCode/>
      <locked>false</locked>
    </instance>
    <instance id="295738">
      <object>oInvCollPH</object>
      <position x="128" y="368"/>
      <creationCode/>
      <locked>false</locked>
    </instance>
    <instance id="295739">
      <object>oInvCollPH</object>
      <position x="112" y="368"/>
      <creationCode/>
      <locked>false</locked>
    </instance>
    <instance id="295740">
      <object>oInvCollPH</object>
      <position x="96" y="368"/>
      <creationCode/>
      <locked>false</locked>
    </instance>
    <instance id="295741">
      <object>oInvCollPH</object>
      <position x="80" y="368"/>
      <creationCode/>
      <locked>false</locked>
    </instance>
    <instance id="295742">
      <object>oInvCollPH</object>
      <position x="528" y="368"/>
      <creationCode/>
      <locked>false</locked>
    </instance>
    <instance id="295743">
      <object>oInvCollPH</object>
      <position x="544" y="368"/>
      <creationCode/>
      <locked>false</locked>
    </instance>
    <instance id="295744">
      <object>oInvCollPH</object>
      <position x="560" y="368"/>
      <creationCode/>
      <locked>false</locked>
    </instance>
    <instance id="295745">
      <object>oInvCollPH</object>
      <position x="576" y="368"/>
      <creationCode/>
      <locked>false</locked>
    </instance>
    <instance id="295746">
      <object>oInvCollPH</object>
      <position x="592" y="368"/>
      <creationCode/>
      <locked>false</locked>
    </instance>
    <instance id="295747">
      <object>oInvCollPH</object>
      <position x="160" y="368"/>
      <creationCode/>
      <locked>false</locked>
    </instance>
    <instance id="295748">
      <object>oInvCollPH</object>
      <position x="176" y="368"/>
      <creationCode/>
      <locked>false</locked>
    </instance>
    <instance id="295749">
      <object>oInvCollPH</object>
      <position x="192" y="368"/>
      <creationCode/>
      <locked>false</locked>
    </instance>
    <instance id="295750">
      <object>oInvCollPH</object>
      <position x="208" y="368"/>
      <creationCode/>
      <locked>false</locked>
    </instance>
    <instance id="295751">
      <object>oInvCollPH</object>
      <position x="224" y="368"/>
      <creationCode/>
      <locked>false</locked>
    </instance>
    <instance id="295752">
      <object>oInvCollPH</object>
      <position x="240" y="368"/>
      <creationCode/>
      <locked>false</locked>
    </instance>
    <instance id="295753">
      <object>oInvCollPH</object>
      <position x="240" y="384"/>
      <creationCode/>
      <locked>false</locked>
    </instance>
    <instance id="295754">
      <object>oInvCollPH</object>
      <position x="240" y="400"/>
      <creationCode/>
      <locked>false</locked>
    </instance>
    <instance id="295755">
      <object>oInvCollPH</object>
      <position x="240" y="416"/>
      <creationCode/>
      <locked>false</locked>
    </instance>
    <instance id="295756">
      <object>oInvCollPH</object>
      <position x="352" y="384"/>
      <creationCode/>
      <locked>false</locked>
    </instance>
    <instance id="295757">
      <object>oInvCollPH</object>
      <position x="352" y="400"/>
      <creationCode/>
      <locked>false</locked>
    </instance>
    <instance id="295758">
      <object>oInvCollPH</object>
      <position x="352" y="416"/>
      <creationCode/>
      <locked>false</locked>
    </instance>
    <instance id="295759">
      <object>oInvCollPH</object>
      <position x="368" y="368"/>
      <creationCode/>
      <locked>false</locked>
    </instance>
    <instance id="295760">
      <object>oInvCollPH</object>
      <position x="384" y="368"/>
      <creationCode/>
      <locked>false</locked>
    </instance>
    <instance id="295761">
      <object>oInvCollPH</object>
      <position x="400" y="368"/>
      <creationCode/>
      <locked>false</locked>
    </instance>
    <instance id="295762">
      <object>oInvCollPH</object>
      <position x="416" y="368"/>
      <creationCode/>
      <locked>false</locked>
    </instance>
    <instance id="295763">
      <object>oInvCollPH</object>
      <position x="432" y="368"/>
      <creationCode/>
      <locked>false</locked>
    </instance>
    <instance id="295764">
      <object>oInvCollPH</object>
      <position x="448" y="368"/>
      <creationCode/>
      <locked>false</locked>
    </instance>
    <instance id="295765">
      <object>oInvCollPH</object>
      <position x="464" y="368"/>
      <creationCode/>
      <locked>false</locked>
    </instance>
    <instance id="295766">
      <object>oInvCollPH</object>
      <position x="480" y="368"/>
      <creationCode/>
      <locked>false</locked>
    </instance>
    <instance id="295767">
      <object>oInvCollPH</object>
      <position x="496" y="368"/>
      <creationCode/>
      <locked>false</locked>
    </instance>
    <instance id="295768">
      <object>oInvCollPH</object>
      <position x="512" y="368"/>
      <creationCode/>
      <locked>false</locked>
    </instance>
    <instance id="295558">
      <object>oInvisibleSolid</object>
      <position x="0" y="0"/>
      <creationCode>image_xscale=38
image_yscale=2</creationCode>
      <locked>false</locked>
    </instance>
    <instance id="295559">
      <object>oInvisibleSolid</object>
      <position x="0" y="32"/>
      <creationCode>image_xscale=4
image_yscale=17</creationCode>
      <locked>false</locked>
    </instance>
    <instance id="295560">
      <object>oInvisibleSolid</object>
      <position x="544" y="32"/>
      <creationCode>image_xscale=4
image_yscale=17</creationCode>
      <locked>false</locked>
    </instance>
    <instance id="295561">
      <object>oInvisibleSolid</object>
      <position x="0" y="368"/>
      <creationCode>image_xscale=16
image_yscale=5</creationCode>
      <locked>false</locked>
    </instance>
    <instance id="295672">
      <object>oInvisibleSolid</object>
      <position x="112" y="112"/>
      <creationCode>image_yscale=5</creationCode>
      <locked>false</locked>
    </instance>
    <instance id="295673">
      <object>oInvisibleSolid</object>
      <position x="128" y="144"/>
      <creationCode>image_xscale=4</creationCode>
      <locked>false</locked>
    </instance>
    <instance id="295674">
      <object>oInvisibleSolid</object>
      <position x="272" y="112"/>
      <creationCode>image_xscale=4
image_yscale=5</creationCode>
      <locked>false</locked>
    </instance>
    <instance id="295675">
      <object>oInvisibleSolid</object>
      <position x="416" y="144"/>
      <creationCode>image_xscale=4</creationCode>
      <locked>false</locked>
    </instance>
    <instance id="295676">
      <object>oInvisibleSolid</object>
      <position x="480" y="112"/>
      <creationCode>image_yscale=5</creationCode>
      <locked>false</locked>
    </instance>
    <instance id="295677">
      <object>oInvisibleSolid</object>
      <position x="352" y="272"/>
      <creationCode>image_xscale=6</creationCode>
      <locked>false</locked>
    </instance>
    <instance id="295678">
      <object>oInvisibleSolid</object>
      <position x="160" y="272"/>
      <creationCode>image_xscale=6</creationCode>
      <locked>false</locked>
    </instance>
    <instance id="295726">
      <object>oInvisibleSolid</object>
      <position x="256" y="432"/>
      <creationCode>image_xscale=6</creationCode>
      <locked>false</locked>
    </instance>
    <instance id="295727">
      <object>oInvisibleSolid</object>
      <position x="352" y="368"/>
      <creationCode>image_xscale=16
image_yscale=5</creationCode>
      <locked>false</locked>
    </instance>
  </instances>
  <tiles>
    <tile id="10365980">
      <background>tileMetF</background>
      <backgroundPosition x="0" y="32"/>
      <roomPosition x="544" y="368"/>
      <size height="16" width="64"/>
      <depth>10</depth>
      <locked>false</locked>
    </tile>
    <tile id="10365982">
      <background>tileMetF</background>
      <backgroundPosition x="32" y="48"/>
      <roomPosition x="576" y="288"/>
      <size height="16" width="32"/>
      <depth>10</depth>
      <locked>false</locked>
    </tile>
    <tile id="10365983">
      <background>tileMetF</background>
      <backgroundPosition x="0" y="48"/>
      <roomPosition x="560" y="288"/>
      <size height="16" width="16"/>
      <depth>10</depth>
      <locked>false</locked>
    </tile>
    <tile id="10365984">
      <background>tileMetF</background>
      <backgroundPosition x="80" y="112"/>
      <roomPosition x="544" y="288"/>
      <size height="16" width="16"/>
      <depth>10</depth>
      <locked>false</locked>
    </tile>
    <tile id="10365985">
      <background>tileMetF</background>
      <backgroundPosition x="64" y="16"/>
      <roomPosition x="544" y="240"/>
      <size height="48" width="16"/>
      <depth>10</depth>
      <locked>false</locked>
    </tile>
    <tile id="10365987">
      <background>tileMetF</background>
      <backgroundPosition x="64" y="16"/>
      <roomPosition x="544" y="208"/>
      <size height="32" width="16"/>
      <depth>10</depth>
      <locked>false</locked>
    </tile>
    <tile id="10365988">
      <background>tileMetF</background>
      <backgroundPosition x="64" y="16"/>
      <roomPosition x="544" y="176"/>
      <size height="32" width="16"/>
      <depth>10</depth>
      <locked>false</locked>
    </tile>
    <tile id="10365989">
      <background>tileMetF</background>
      <backgroundPosition x="64" y="16"/>
      <roomPosition x="544" y="144"/>
      <size height="32" width="16"/>
      <depth>10</depth>
      <locked>false</locked>
    </tile>
    <tile id="10365990">
      <background>tileMetF</background>
      <backgroundPosition x="64" y="16"/>
      <roomPosition x="544" y="112"/>
      <size height="32" width="16"/>
      <depth>10</depth>
      <locked>false</locked>
    </tile>
    <tile id="10365991">
      <background>tileMetF</background>
      <backgroundPosition x="64" y="16"/>
      <roomPosition x="544" y="80"/>
      <size height="32" width="16"/>
      <depth>10</depth>
      <locked>false</locked>
    </tile>
    <tile id="10365992">
      <background>tileMetF</background>
      <backgroundPosition x="64" y="0"/>
      <roomPosition x="544" y="32"/>
      <size height="48" width="16"/>
      <depth>10</depth>
      <locked>false</locked>
    </tile>
    <tile id="10365993">
      <background>tileMetF</background>
      <backgroundPosition x="112" y="128"/>
      <roomPosition x="544" y="16"/>
      <size height="16" width="16"/>
      <depth>10</depth>
      <locked>false</locked>
    </tile>
    <tile id="10365994">
      <background>tileMetF</background>
      <backgroundPosition x="16" y="48"/>
      <roomPosition x="496" y="16"/>
      <size height="16" width="48"/>
      <depth>10</depth>
      <locked>false</locked>
    </tile>
    <tile id="10366004">
      <background>tileMetF</background>
      <backgroundPosition x="16" y="48"/>
      <roomPosition x="176" y="16"/>
      <size height="16" width="32"/>
      <depth>10</depth>
      <locked>false</locked>
    </tile>
    <tile id="10366005">
      <background>tileMetF</background>
      <backgroundPosition x="16" y="48"/>
      <roomPosition x="208" y="16"/>
      <size height="16" width="32"/>
      <depth>10</depth>
      <locked>false</locked>
    </tile>
    <tile id="10366006">
      <background>tileMetF</background>
      <backgroundPosition x="16" y="48"/>
      <roomPosition x="240" y="16"/>
      <size height="16" width="32"/>
      <depth>10</depth>
      <locked>false</locked>
    </tile>
    <tile id="10366007">
      <background>tileMetF</background>
      <backgroundPosition x="16" y="48"/>
      <roomPosition x="272" y="16"/>
      <size height="16" width="32"/>
      <depth>10</depth>
      <locked>false</locked>
    </tile>
    <tile id="10366008">
      <background>tileMetF</background>
      <backgroundPosition x="16" y="48"/>
      <roomPosition x="304" y="16"/>
      <size height="16" width="32"/>
      <depth>10</depth>
      <locked>false</locked>
    </tile>
    <tile id="10366009">
      <background>tileMetF</background>
      <backgroundPosition x="16" y="48"/>
      <roomPosition x="336" y="16"/>
      <size height="16" width="32"/>
      <depth>10</depth>
      <locked>false</locked>
    </tile>
    <tile id="10366010">
      <background>tileMetF</background>
      <backgroundPosition x="16" y="48"/>
      <roomPosition x="368" y="16"/>
      <size height="16" width="32"/>
      <depth>10</depth>
      <locked>false</locked>
    </tile>
    <tile id="10366011">
      <background>tileMetF</background>
      <backgroundPosition x="16" y="48"/>
      <roomPosition x="400" y="16"/>
      <size height="16" width="32"/>
      <depth>10</depth>
      <locked>false</locked>
    </tile>
    <tile id="10366012">
      <background>tileMetF</background>
      <backgroundPosition x="16" y="48"/>
      <roomPosition x="432" y="16"/>
      <size height="16" width="32"/>
      <depth>10</depth>
      <locked>false</locked>
    </tile>
    <tile id="10366013">
      <background>tileMetF</background>
      <backgroundPosition x="16" y="48"/>
      <roomPosition x="464" y="16"/>
      <size height="16" width="32"/>
      <depth>10</depth>
      <locked>false</locked>
    </tile>
    <tile id="10366014">
      <background>tileMetF</background>
      <backgroundPosition x="16" y="48"/>
      <roomPosition x="144" y="16"/>
      <size height="16" width="32"/>
      <depth>10</depth>
      <locked>false</locked>
    </tile>
    <tile id="10366015">
      <background>tileMetF</background>
      <backgroundPosition x="16" y="48"/>
      <roomPosition x="112" y="16"/>
      <size height="16" width="32"/>
      <depth>10</depth>
      <locked>false</locked>
    </tile>
    <tile id="10366020">
      <background>tileMetF</background>
      <backgroundPosition x="0" y="48"/>
      <roomPosition x="64" y="16"/>
      <size height="16" width="48"/>
      <depth>10</depth>
      <locked>false</locked>
    </tile>
    <tile id="10366021">
      <background>tileMetF</background>
      <backgroundPosition x="112" y="128"/>
      <roomPosition x="48" y="16"/>
      <size height="16" width="16"/>
      <depth>10</depth>
      <locked>false</locked>
    </tile>
    <tile id="10366022">
      <background>tileMetF</background>
      <backgroundPosition x="80" y="0"/>
      <roomPosition x="48" y="32"/>
      <size height="48" width="16"/>
      <depth>10</depth>
      <locked>false</locked>
    </tile>
    <tile id="10366023">
      <background>tileMetF</background>
      <backgroundPosition x="80" y="16"/>
      <roomPosition x="48" y="80"/>
      <size height="32" width="16"/>
      <depth>10</depth>
      <locked>false</locked>
    </tile>
    <tile id="10366024">
      <background>tileMetF</background>
      <backgroundPosition x="80" y="16"/>
      <roomPosition x="48" y="112"/>
      <size height="32" width="16"/>
      <depth>10</depth>
      <locked>false</locked>
    </tile>
    <tile id="10366025">
      <background>tileMetF</background>
      <backgroundPosition x="80" y="16"/>
      <roomPosition x="48" y="144"/>
      <size height="32" width="16"/>
      <depth>10</depth>
      <locked>false</locked>
    </tile>
    <tile id="10366026">
      <background>tileMetF</background>
      <backgroundPosition x="80" y="16"/>
      <roomPosition x="48" y="176"/>
      <size height="32" width="16"/>
      <depth>10</depth>
      <locked>false</locked>
    </tile>
    <tile id="10366027">
      <background>tileMetF</background>
      <backgroundPosition x="80" y="16"/>
      <roomPosition x="48" y="208"/>
      <size height="32" width="16"/>
      <depth>10</depth>
      <locked>false</locked>
    </tile>
    <tile id="10366030">
      <background>tileMetF</background>
      <backgroundPosition x="96" y="112"/>
      <roomPosition x="48" y="288"/>
      <size height="16" width="16"/>
      <depth>10</depth>
      <locked>false</locked>
    </tile>
    <tile id="10366031">
      <background>tileMetF</background>
      <backgroundPosition x="32" y="48"/>
      <roomPosition x="16" y="288"/>
      <size height="16" width="32"/>
      <depth>10</depth>
      <locked>false</locked>
    </tile>
    <tile id="10366032">
      <background>tileMetF</background>
      <backgroundPosition x="0" y="48"/>
      <roomPosition x="0" y="288"/>
      <size height="16" width="16"/>
      <depth>10</depth>
      <locked>false</locked>
    </tile>
    <tile id="10366033">
      <background>tileMetF</background>
      <backgroundPosition x="0" y="32"/>
      <roomPosition x="0" y="368"/>
      <size height="16" width="64"/>
      <depth>10</depth>
      <locked>false</locked>
    </tile>
    <tile id="10366034">
      <background>tileMetF</background>
      <backgroundPosition x="32" y="96"/>
      <roomPosition x="64" y="368"/>
      <size height="16" width="16"/>
      <depth>10</depth>
      <locked>false</locked>
    </tile>
    <tile id="10366035">
      <background>tileMetF</background>
      <backgroundPosition x="32" y="96"/>
      <roomPosition x="528" y="368"/>
      <size height="16" width="16"/>
      <depth>10</depth>
      <locked>false</locked>
    </tile>
    <tile id="10366036">
      <background>tileMetF</background>
      <backgroundPosition x="0" y="0"/>
      <roomPosition x="80" y="368"/>
      <size height="16" width="48"/>
      <depth>10</depth>
      <locked>false</locked>
    </tile>
    <tile id="10366037">
      <background>tileMetF</background>
      <backgroundPosition x="16" y="0"/>
      <roomPosition x="128" y="368"/>
      <size height="16" width="32"/>
      <depth>10</depth>
      <locked>false</locked>
    </tile>
    <tile id="10366038">
      <background>tileMetF</background>
      <backgroundPosition x="16" y="0"/>
      <roomPosition x="160" y="368"/>
      <size height="16" width="32"/>
      <depth>10</depth>
      <locked>false</locked>
    </tile>
    <tile id="10366046">
      <background>tileMetF</background>
      <backgroundPosition x="16" y="0"/>
      <roomPosition x="416" y="368"/>
      <size height="16" width="32"/>
      <depth>10</depth>
      <locked>false</locked>
    </tile>
    <tile id="10366047">
      <background>tileMetF</background>
      <backgroundPosition x="16" y="0"/>
      <roomPosition x="448" y="368"/>
      <size height="16" width="32"/>
      <depth>10</depth>
      <locked>false</locked>
    </tile>
    <tile id="10366048">
      <background>tileMetF</background>
      <backgroundPosition x="16" y="0"/>
      <roomPosition x="480" y="368"/>
      <size height="16" width="48"/>
      <depth>10</depth>
      <locked>false</locked>
    </tile>
    <tile id="10366051">
      <background>tileMetF</background>
      <backgroundPosition x="16" y="0"/>
      <roomPosition x="192" y="368"/>
      <size height="16" width="48"/>
      <depth>10</depth>
      <locked>false</locked>
    </tile>
    <tile id="10366052">
      <background>tileMetF</background>
      <backgroundPosition x="0" y="0"/>
      <roomPosition x="368" y="368"/>
      <size height="16" width="48"/>
      <depth>10</depth>
      <locked>false</locked>
    </tile>
    <tile id="10366056">
      <background>tileMetF</background>
      <backgroundPosition x="0" y="32"/>
      <roomPosition x="256" y="432"/>
      <size height="16" width="48"/>
      <depth>10</depth>
      <locked>false</locked>
    </tile>
    <tile id="10366057">
      <background>tileMetF</background>
      <backgroundPosition x="16" y="32"/>
      <roomPosition x="304" y="432"/>
      <size height="16" width="48"/>
      <depth>10</depth>
      <locked>false</locked>
    </tile>
    <tile id="10366058">
      <background>tileMetF</background>
      <backgroundPosition x="0" y="144"/>
      <roomPosition x="0" y="384"/>
      <size height="16" width="32"/>
      <depth>10</depth>
      <locked>false</locked>
    </tile>
    <tile id="10366059">
      <background>tileMetF</background>
      <backgroundPosition x="0" y="144"/>
      <roomPosition x="32" y="384"/>
      <size height="16" width="32"/>
      <depth>10</depth>
      <locked>false</locked>
    </tile>
    <tile id="10366060">
      <background>tileMetF</background>
      <backgroundPosition x="0" y="144"/>
      <roomPosition x="64" y="384"/>
      <size height="16" width="32"/>
      <depth>10</depth>
      <locked>false</locked>
    </tile>
    <tile id="10366061">
      <background>tileMetF</background>
      <backgroundPosition x="0" y="144"/>
      <roomPosition x="96" y="384"/>
      <size height="16" width="32"/>
      <depth>10</depth>
      <locked>false</locked>
    </tile>
    <tile id="10366062">
      <background>tileMetF</background>
      <backgroundPosition x="0" y="144"/>
      <roomPosition x="128" y="384"/>
      <size height="16" width="32"/>
      <depth>10</depth>
      <locked>false</locked>
    </tile>
    <tile id="10366063">
      <background>tileMetF</background>
      <backgroundPosition x="0" y="144"/>
      <roomPosition x="160" y="384"/>
      <size height="16" width="32"/>
      <depth>10</depth>
      <locked>false</locked>
    </tile>
    <tile id="10366064">
      <background>tileMetF</background>
      <backgroundPosition x="0" y="144"/>
      <roomPosition x="192" y="384"/>
      <size height="16" width="32"/>
      <depth>10</depth>
      <locked>false</locked>
    </tile>
    <tile id="10366070">
      <background>tileMetF</background>
      <backgroundPosition x="0" y="144"/>
      <roomPosition x="384" y="384"/>
      <size height="16" width="32"/>
      <depth>10</depth>
      <locked>false</locked>
    </tile>
    <tile id="10366071">
      <background>tileMetF</background>
      <backgroundPosition x="0" y="144"/>
      <roomPosition x="416" y="384"/>
      <size height="16" width="32"/>
      <depth>10</depth>
      <locked>false</locked>
    </tile>
    <tile id="10366072">
      <background>tileMetF</background>
      <backgroundPosition x="0" y="144"/>
      <roomPosition x="448" y="384"/>
      <size height="16" width="32"/>
      <depth>10</depth>
      <locked>false</locked>
    </tile>
    <tile id="10366073">
      <background>tileMetF</background>
      <backgroundPosition x="0" y="144"/>
      <roomPosition x="480" y="384"/>
      <size height="16" width="32"/>
      <depth>10</depth>
      <locked>false</locked>
    </tile>
    <tile id="10366074">
      <background>tileMetF</background>
      <backgroundPosition x="0" y="144"/>
      <roomPosition x="512" y="384"/>
      <size height="16" width="32"/>
      <depth>10</depth>
      <locked>false</locked>
    </tile>
    <tile id="10366075">
      <background>tileMetF</background>
      <backgroundPosition x="0" y="144"/>
      <roomPosition x="544" y="384"/>
      <size height="16" width="32"/>
      <depth>10</depth>
      <locked>false</locked>
    </tile>
    <tile id="10366076">
      <background>tileMetF</background>
      <backgroundPosition x="0" y="144"/>
      <roomPosition x="576" y="384"/>
      <size height="16" width="32"/>
      <depth>10</depth>
      <locked>false</locked>
    </tile>
    <tile id="10366077">
      <background>tileMetF</background>
      <backgroundPosition x="0" y="144"/>
      <roomPosition x="0" y="272"/>
      <size height="16" width="32"/>
      <depth>10</depth>
      <locked>false</locked>
    </tile>
    <tile id="10366079">
      <background>tileMetF</background>
      <backgroundPosition x="32" y="128"/>
      <roomPosition x="32" y="256"/>
      <size height="32" width="16"/>
      <depth>10</depth>
      <locked>false</locked>
    </tile>
    <tile id="10366080">
      <background>tileMetF</background>
      <backgroundPosition x="32" y="128"/>
      <roomPosition x="32" y="224"/>
      <size height="32" width="16"/>
      <depth>10</depth>
      <locked>false</locked>
    </tile>
    <tile id="10366081">
      <background>tileMetF</background>
      <backgroundPosition x="32" y="128"/>
      <roomPosition x="32" y="192"/>
      <size height="32" width="16"/>
      <depth>10</depth>
      <locked>false</locked>
    </tile>
    <tile id="10366082">
      <background>tileMetF</background>
      <backgroundPosition x="32" y="128"/>
      <roomPosition x="32" y="160"/>
      <size height="32" width="16"/>
      <depth>10</depth>
      <locked>false</locked>
    </tile>
    <tile id="10366083">
      <background>tileMetF</background>
      <backgroundPosition x="32" y="128"/>
      <roomPosition x="32" y="128"/>
      <size height="32" width="16"/>
      <depth>10</depth>
      <locked>false</locked>
    </tile>
    <tile id="10366084">
      <background>tileMetF</background>
      <backgroundPosition x="32" y="128"/>
      <roomPosition x="32" y="96"/>
      <size height="32" width="16"/>
      <depth>10</depth>
      <locked>false</locked>
    </tile>
    <tile id="10366085">
      <background>tileMetF</background>
      <backgroundPosition x="32" y="128"/>
      <roomPosition x="32" y="64"/>
      <size height="32" width="16"/>
      <depth>10</depth>
      <locked>false</locked>
    </tile>
    <tile id="10366086">
      <background>tileMetF</background>
      <backgroundPosition x="32" y="128"/>
      <roomPosition x="32" y="32"/>
      <size height="32" width="16"/>
      <depth>10</depth>
      <locked>false</locked>
    </tile>
    <tile id="10366087">
      <background>tileMetF</background>
      <backgroundPosition x="32" y="128"/>
      <roomPosition x="32" y="0"/>
      <size height="32" width="16"/>
      <depth>10</depth>
      <locked>false</locked>
    </tile>
    <tile id="10366088">
      <background>tileMetF</background>
      <backgroundPosition x="0" y="144"/>
      <roomPosition x="48" y="0"/>
      <size height="16" width="32"/>
      <depth>10</depth>
      <locked>false</locked>
    </tile>
    <tile id="10366089">
      <background>tileMetF</background>
      <backgroundPosition x="0" y="144"/>
      <roomPosition x="80" y="0"/>
      <size height="16" width="32"/>
      <depth>10</depth>
      <locked>false</locked>
    </tile>
    <tile id="10366090">
      <background>tileMetF</background>
      <backgroundPosition x="0" y="144"/>
      <roomPosition x="112" y="0"/>
      <size height="16" width="32"/>
      <depth>10</depth>
      <locked>false</locked>
    </tile>
    <tile id="10366091">
      <background>tileMetF</background>
      <backgroundPosition x="0" y="144"/>
      <roomPosition x="144" y="0"/>
      <size height="16" width="32"/>
      <depth>10</depth>
      <locked>false</locked>
    </tile>
    <tile id="10366092">
      <background>tileMetF</background>
      <backgroundPosition x="0" y="144"/>
      <roomPosition x="176" y="0"/>
      <size height="16" width="32"/>
      <depth>10</depth>
      <locked>false</locked>
    </tile>
    <tile id="10366093">
      <background>tileMetF</background>
      <backgroundPosition x="0" y="144"/>
      <roomPosition x="208" y="0"/>
      <size height="16" width="32"/>
      <depth>10</depth>
      <locked>false</locked>
    </tile>
    <tile id="10366094">
      <background>tileMetF</background>
      <backgroundPosition x="0" y="144"/>
      <roomPosition x="240" y="0"/>
      <size height="16" width="32"/>
      <depth>10</depth>
      <locked>false</locked>
    </tile>
    <tile id="10366095">
      <background>tileMetF</background>
      <backgroundPosition x="0" y="144"/>
      <roomPosition x="272" y="0"/>
      <size height="16" width="32"/>
      <depth>10</depth>
      <locked>false</locked>
    </tile>
    <tile id="10366096">
      <background>tileMetF</background>
      <backgroundPosition x="0" y="144"/>
      <roomPosition x="304" y="0"/>
      <size height="16" width="32"/>
      <depth>10</depth>
      <locked>false</locked>
    </tile>
    <tile id="10366097">
      <background>tileMetF</background>
      <backgroundPosition x="0" y="144"/>
      <roomPosition x="336" y="0"/>
      <size height="16" width="32"/>
      <depth>10</depth>
      <locked>false</locked>
    </tile>
    <tile id="10366098">
      <background>tileMetF</background>
      <backgroundPosition x="0" y="144"/>
      <roomPosition x="368" y="0"/>
      <size height="16" width="32"/>
      <depth>10</depth>
      <locked>false</locked>
    </tile>
    <tile id="10366099">
      <background>tileMetF</background>
      <backgroundPosition x="0" y="144"/>
      <roomPosition x="400" y="0"/>
      <size height="16" width="32"/>
      <depth>10</depth>
      <locked>false</locked>
    </tile>
    <tile id="10366100">
      <background>tileMetF</background>
      <backgroundPosition x="0" y="144"/>
      <roomPosition x="432" y="0"/>
      <size height="16" width="32"/>
      <depth>10</depth>
      <locked>false</locked>
    </tile>
    <tile id="10366101">
      <background>tileMetF</background>
      <backgroundPosition x="0" y="144"/>
      <roomPosition x="464" y="0"/>
      <size height="16" width="32"/>
      <depth>10</depth>
      <locked>false</locked>
    </tile>
    <tile id="10366102">
      <background>tileMetF</background>
      <backgroundPosition x="0" y="144"/>
      <roomPosition x="496" y="0"/>
      <size height="16" width="32"/>
      <depth>10</depth>
      <locked>false</locked>
    </tile>
    <tile id="10366103">
      <background>tileMetF</background>
      <backgroundPosition x="0" y="144"/>
      <roomPosition x="528" y="0"/>
      <size height="16" width="32"/>
      <depth>10</depth>
      <locked>false</locked>
    </tile>
    <tile id="10366104">
      <background>tileMetF</background>
      <backgroundPosition x="0" y="144"/>
      <roomPosition x="576" y="272"/>
      <size height="16" width="32"/>
      <depth>10</depth>
      <locked>false</locked>
    </tile>
    <tile id="10366105">
      <background>tileMetF</background>
      <backgroundPosition x="32" y="128"/>
      <roomPosition x="560" y="0"/>
      <size height="32" width="16"/>
      <depth>10</depth>
      <locked>false</locked>
    </tile>
    <tile id="10366106">
      <background>tileMetF</background>
      <backgroundPosition x="32" y="128"/>
      <roomPosition x="560" y="32"/>
      <size height="32" width="16"/>
      <depth>10</depth>
      <locked>false</locked>
    </tile>
    <tile id="10366107">
      <background>tileMetF</background>
      <backgroundPosition x="32" y="128"/>
      <roomPosition x="560" y="64"/>
      <size height="32" width="16"/>
      <depth>10</depth>
      <locked>false</locked>
    </tile>
    <tile id="10366108">
      <background>tileMetF</background>
      <backgroundPosition x="32" y="128"/>
      <roomPosition x="560" y="96"/>
      <size height="32" width="16"/>
      <depth>10</depth>
      <locked>false</locked>
    </tile>
    <tile id="10366109">
      <background>tileMetF</background>
      <backgroundPosition x="32" y="128"/>
      <roomPosition x="560" y="128"/>
      <size height="32" width="16"/>
      <depth>10</depth>
      <locked>false</locked>
    </tile>
    <tile id="10366110">
      <background>tileMetF</background>
      <backgroundPosition x="32" y="128"/>
      <roomPosition x="560" y="160"/>
      <size height="32" width="16"/>
      <depth>10</depth>
      <locked>false</locked>
    </tile>
    <tile id="10366111">
      <background>tileMetF</background>
      <backgroundPosition x="32" y="128"/>
      <roomPosition x="560" y="192"/>
      <size height="32" width="16"/>
      <depth>10</depth>
      <locked>false</locked>
    </tile>
    <tile id="10366112">
      <background>tileMetF</background>
      <backgroundPosition x="32" y="128"/>
      <roomPosition x="560" y="224"/>
      <size height="32" width="16"/>
      <depth>10</depth>
      <locked>false</locked>
    </tile>
    <tile id="10366113">
      <background>tileMetF</background>
      <backgroundPosition x="32" y="128"/>
      <roomPosition x="560" y="256"/>
      <size height="32" width="16"/>
      <depth>10</depth>
      <locked>false</locked>
    </tile>
    <tile id="10366115">
      <background>tileMetF</background>
      <backgroundPosition x="80" y="128"/>
      <roomPosition x="0" y="432"/>
      <size height="16" width="32"/>
      <depth>10</depth>
      <locked>false</locked>
    </tile>
    <tile id="10366116">
      <background>tileMetF</background>
      <backgroundPosition x="80" y="128"/>
      <roomPosition x="32" y="432"/>
      <size height="16" width="32"/>
      <depth>10</depth>
      <locked>false</locked>
    </tile>
    <tile id="10366117">
      <background>tileMetF</background>
      <backgroundPosition x="80" y="128"/>
      <roomPosition x="64" y="432"/>
      <size height="16" width="32"/>
      <depth>10</depth>
      <locked>false</locked>
    </tile>
    <tile id="10366118">
      <background>tileMetF</background>
      <backgroundPosition x="80" y="128"/>
      <roomPosition x="96" y="432"/>
      <size height="16" width="32"/>
      <depth>10</depth>
      <locked>false</locked>
    </tile>
    <tile id="10366119">
      <background>tileMetF</background>
      <backgroundPosition x="80" y="128"/>
      <roomPosition x="128" y="432"/>
      <size height="16" width="32"/>
      <depth>10</depth>
      <locked>false</locked>
    </tile>
    <tile id="10366120">
      <background>tileMetF</background>
      <backgroundPosition x="80" y="128"/>
      <roomPosition x="160" y="432"/>
      <size height="16" width="32"/>
      <depth>10</depth>
      <locked>false</locked>
    </tile>
    <tile id="10366121">
      <background>tileMetF</background>
      <backgroundPosition x="80" y="128"/>
      <roomPosition x="192" y="432"/>
      <size height="16" width="32"/>
      <depth>10</depth>
      <locked>false</locked>
    </tile>
    <tile id="10366127">
      <background>tileMetF</background>
      <backgroundPosition x="80" y="128"/>
      <roomPosition x="384" y="432"/>
      <size height="16" width="32"/>
      <depth>10</depth>
      <locked>false</locked>
    </tile>
    <tile id="10366128">
      <background>tileMetF</background>
      <backgroundPosition x="80" y="128"/>
      <roomPosition x="416" y="432"/>
      <size height="16" width="32"/>
      <depth>10</depth>
      <locked>false</locked>
    </tile>
    <tile id="10366129">
      <background>tileMetF</background>
      <backgroundPosition x="80" y="128"/>
      <roomPosition x="448" y="432"/>
      <size height="16" width="32"/>
      <depth>10</depth>
      <locked>false</locked>
    </tile>
    <tile id="10366130">
      <background>tileMetF</background>
      <backgroundPosition x="80" y="128"/>
      <roomPosition x="480" y="432"/>
      <size height="16" width="32"/>
      <depth>10</depth>
      <locked>false</locked>
    </tile>
    <tile id="10366131">
      <background>tileMetF</background>
      <backgroundPosition x="80" y="128"/>
      <roomPosition x="512" y="432"/>
      <size height="16" width="32"/>
      <depth>10</depth>
      <locked>false</locked>
    </tile>
    <tile id="10366132">
      <background>tileMetF</background>
      <backgroundPosition x="80" y="128"/>
      <roomPosition x="544" y="432"/>
      <size height="16" width="32"/>
      <depth>10</depth>
      <locked>false</locked>
    </tile>
    <tile id="10366133">
      <background>tileMetF</background>
      <backgroundPosition x="80" y="128"/>
      <roomPosition x="576" y="432"/>
      <size height="16" width="32"/>
      <depth>10</depth>
      <locked>false</locked>
    </tile>
    <tile id="10366134">
      <background>tileMetF</background>
      <backgroundPosition x="80" y="128"/>
      <roomPosition x="0" y="0"/>
      <size height="32" width="32"/>
      <depth>10</depth>
      <locked>false</locked>
    </tile>
    <tile id="10366135">
      <background>tileMetF</background>
      <backgroundPosition x="80" y="128"/>
      <roomPosition x="0" y="32"/>
      <size height="32" width="32"/>
      <depth>10</depth>
      <locked>false</locked>
    </tile>
    <tile id="10366136">
      <background>tileMetF</background>
      <backgroundPosition x="80" y="128"/>
      <roomPosition x="0" y="64"/>
      <size height="32" width="32"/>
      <depth>10</depth>
      <locked>false</locked>
    </tile>
    <tile id="10366137">
      <background>tileMetF</background>
      <backgroundPosition x="80" y="128"/>
      <roomPosition x="0" y="96"/>
      <size height="32" width="32"/>
      <depth>10</depth>
      <locked>false</locked>
    </tile>
    <tile id="10366138">
      <background>tileMetF</background>
      <backgroundPosition x="80" y="128"/>
      <roomPosition x="0" y="128"/>
      <size height="32" width="32"/>
      <depth>10</depth>
      <locked>false</locked>
    </tile>
    <tile id="10366139">
      <background>tileMetF</background>
      <backgroundPosition x="80" y="128"/>
      <roomPosition x="0" y="160"/>
      <size height="32" width="32"/>
      <depth>10</depth>
      <locked>false</locked>
    </tile>
    <tile id="10366140">
      <background>tileMetF</background>
      <backgroundPosition x="80" y="128"/>
      <roomPosition x="0" y="192"/>
      <size height="32" width="32"/>
      <depth>10</depth>
      <locked>false</locked>
    </tile>
    <tile id="10366141">
      <background>tileMetF</background>
      <backgroundPosition x="80" y="128"/>
      <roomPosition x="16" y="224"/>
      <size height="32" width="32"/>
      <depth>10</depth>
      <locked>false</locked>
    </tile>
    <tile id="10366142">
      <background>tileMetF</background>
      <backgroundPosition x="80" y="128"/>
      <roomPosition x="0" y="224"/>
      <size height="32" width="32"/>
      <depth>10</depth>
      <locked>false</locked>
    </tile>
    <tile id="10366144">
      <background>tileMetF</background>
      <backgroundPosition x="80" y="128"/>
      <roomPosition x="576" y="0"/>
      <size height="32" width="32"/>
      <depth>10</depth>
      <locked>false</locked>
    </tile>
    <tile id="10366145">
      <background>tileMetF</background>
      <backgroundPosition x="80" y="128"/>
      <roomPosition x="576" y="32"/>
      <size height="32" width="32"/>
      <depth>10</depth>
      <locked>false</locked>
    </tile>
    <tile id="10366146">
      <background>tileMetF</background>
      <backgroundPosition x="80" y="128"/>
      <roomPosition x="576" y="64"/>
      <size height="32" width="32"/>
      <depth>10</depth>
      <locked>false</locked>
    </tile>
    <tile id="10366147">
      <background>tileMetF</background>
      <backgroundPosition x="80" y="128"/>
      <roomPosition x="576" y="96"/>
      <size height="32" width="32"/>
      <depth>10</depth>
      <locked>false</locked>
    </tile>
    <tile id="10366148">
      <background>tileMetF</background>
      <backgroundPosition x="80" y="128"/>
      <roomPosition x="576" y="128"/>
      <size height="32" width="32"/>
      <depth>10</depth>
      <locked>false</locked>
    </tile>
    <tile id="10366149">
      <background>tileMetF</background>
      <backgroundPosition x="80" y="128"/>
      <roomPosition x="576" y="160"/>
      <size height="32" width="32"/>
      <depth>10</depth>
      <locked>false</locked>
    </tile>
    <tile id="10366150">
      <background>tileMetF</background>
      <backgroundPosition x="80" y="128"/>
      <roomPosition x="576" y="192"/>
      <size height="32" width="32"/>
      <depth>10</depth>
      <locked>false</locked>
    </tile>
    <tile id="10366151">
      <background>tileMetF</background>
      <backgroundPosition x="80" y="128"/>
      <roomPosition x="576" y="224"/>
      <size height="32" width="32"/>
      <depth>10</depth>
      <locked>false</locked>
    </tile>
    <tile id="10366153">
      <background>tileMetF</background>
      <backgroundPosition x="80" y="128"/>
      <roomPosition x="0" y="256"/>
      <size height="16" width="32"/>
      <depth>10</depth>
      <locked>false</locked>
    </tile>
    <tile id="10366154">
      <background>tileMetF</background>
      <backgroundPosition x="80" y="128"/>
      <roomPosition x="576" y="256"/>
      <size height="16" width="32"/>
      <depth>10</depth>
      <locked>false</locked>
    </tile>
    <tile id="10366159">
      <background>tileMetF</background>
      <backgroundPosition x="128" y="160"/>
      <roomPosition x="160" y="272"/>
      <size height="16" width="32"/>
      <depth>10</depth>
      <locked>false</locked>
    </tile>
    <tile id="10366160">
      <background>tileMetF</background>
      <backgroundPosition x="128" y="160"/>
      <roomPosition x="352" y="272"/>
      <size height="16" width="32"/>
      <depth>10</depth>
      <locked>false</locked>
    </tile>
    <tile id="10366161">
      <background>tileMetF</background>
      <backgroundPosition x="144" y="160"/>
      <roomPosition x="224" y="272"/>
      <size height="16" width="32"/>
      <depth>10</depth>
      <locked>false</locked>
    </tile>
    <tile id="10366162">
      <background>tileMetF</background>
      <backgroundPosition x="144" y="160"/>
      <roomPosition x="416" y="272"/>
      <size height="16" width="32"/>
      <depth>10</depth>
      <locked>false</locked>
    </tile>
    <tile id="10366163">
      <background>tileMetF</background>
      <backgroundPosition x="144" y="160"/>
      <roomPosition x="192" y="272"/>
      <size height="16" width="16"/>
      <depth>10</depth>
      <locked>false</locked>
    </tile>
    <tile id="10366164">
      <background>tileMetF</background>
      <backgroundPosition x="144" y="160"/>
      <roomPosition x="208" y="272"/>
      <size height="16" width="16"/>
      <depth>10</depth>
      <locked>false</locked>
    </tile>
    <tile id="10366165">
      <background>tileMetF</background>
      <backgroundPosition x="144" y="160"/>
      <roomPosition x="384" y="272"/>
      <size height="16" width="16"/>
      <depth>10</depth>
      <locked>false</locked>
    </tile>
    <tile id="10366166">
      <background>tileMetF</background>
      <backgroundPosition x="144" y="160"/>
      <roomPosition x="400" y="272"/>
      <size height="16" width="16"/>
      <depth>10</depth>
      <locked>false</locked>
    </tile>
    <tile id="10366168">
      <background>tileMetF</background>
      <backgroundPosition x="128" y="160"/>
      <roomPosition x="128" y="144"/>
      <size height="16" width="32"/>
      <depth>10</depth>
      <locked>false</locked>
    </tile>
    <tile id="10366169">
      <background>tileMetF</background>
      <backgroundPosition x="128" y="160"/>
      <roomPosition x="416" y="144"/>
      <size height="16" width="32"/>
      <depth>10</depth>
      <locked>false</locked>
    </tile>
    <tile id="10366170">
      <background>tileMetF</background>
      <backgroundPosition x="144" y="160"/>
      <roomPosition x="160" y="144"/>
      <size height="16" width="32"/>
      <depth>10</depth>
      <locked>false</locked>
    </tile>
    <tile id="10366171">
      <background>tileMetF</background>
      <backgroundPosition x="144" y="160"/>
      <roomPosition x="448" y="144"/>
      <size height="16" width="32"/>
      <depth>10</depth>
      <locked>false</locked>
    </tile>
    <tile id="10366172">
      <background>tileMetF</background>
      <backgroundPosition x="32" y="80"/>
      <roomPosition x="480" y="112"/>
      <size height="16" width="16"/>
      <depth>10</depth>
      <locked>false</locked>
    </tile>
    <tile id="10366173">
      <background>tileMetF</background>
      <backgroundPosition x="32" y="80"/>
      <roomPosition x="480" y="128"/>
      <size height="16" width="16"/>
      <depth>10</depth>
      <locked>false</locked>
    </tile>
    <tile id="10366174">
      <background>tileMetF</background>
      <backgroundPosition x="32" y="80"/>
      <roomPosition x="480" y="144"/>
      <size height="16" width="16"/>
      <depth>10</depth>
      <locked>false</locked>
    </tile>
    <tile id="10366175">
      <background>tileMetF</background>
      <backgroundPosition x="32" y="80"/>
      <roomPosition x="480" y="160"/>
      <size height="16" width="16"/>
      <depth>10</depth>
      <locked>false</locked>
    </tile>
    <tile id="10366176">
      <background>tileMetF</background>
      <backgroundPosition x="32" y="80"/>
      <roomPosition x="480" y="176"/>
      <size height="16" width="16"/>
      <depth>10</depth>
      <locked>false</locked>
    </tile>
    <tile id="10366177">
      <background>tileMetF</background>
      <backgroundPosition x="32" y="80"/>
      <roomPosition x="112" y="112"/>
      <size height="16" width="16"/>
      <depth>10</depth>
      <locked>false</locked>
    </tile>
    <tile id="10366178">
      <background>tileMetF</background>
      <backgroundPosition x="32" y="80"/>
      <roomPosition x="112" y="128"/>
      <size height="16" width="16"/>
      <depth>10</depth>
      <locked>false</locked>
    </tile>
    <tile id="10366179">
      <background>tileMetF</background>
      <backgroundPosition x="32" y="80"/>
      <roomPosition x="112" y="144"/>
      <size height="16" width="16"/>
      <depth>10</depth>
      <locked>false</locked>
    </tile>
    <tile id="10366180">
      <background>tileMetF</background>
      <backgroundPosition x="32" y="80"/>
      <roomPosition x="112" y="160"/>
      <size height="16" width="16"/>
      <depth>10</depth>
      <locked>false</locked>
    </tile>
    <tile id="10366181">
      <background>tileMetF</background>
      <backgroundPosition x="32" y="80"/>
      <roomPosition x="112" y="176"/>
      <size height="16" width="16"/>
      <depth>10</depth>
      <locked>false</locked>
    </tile>
    <tile id="10366196">
      <background>tileMetF</background>
      <backgroundPosition x="96" y="96"/>
      <roomPosition x="320" y="112"/>
      <size height="16" width="16"/>
      <depth>10</depth>
      <locked>false</locked>
    </tile>
    <tile id="10366198">
      <background>tileMetF</background>
      <backgroundPosition x="80" y="96"/>
      <roomPosition x="272" y="112"/>
      <size height="16" width="16"/>
      <depth>10</depth>
      <locked>false</locked>
    </tile>
    <tile id="10366199">
      <background>tileMetF</background>
      <backgroundPosition x="80" y="112"/>
      <roomPosition x="272" y="176"/>
      <size height="16" width="16"/>
      <depth>10</depth>
      <locked>false</locked>
    </tile>
    <tile id="10366200">
      <background>tileMetF</background>
      <backgroundPosition x="96" y="112"/>
      <roomPosition x="320" y="176"/>
      <size height="16" width="16"/>
      <depth>10</depth>
      <locked>false</locked>
    </tile>
    <tile id="10366201">
      <background>tileMetF</background>
      <backgroundPosition x="0" y="0"/>
      <roomPosition x="288" y="112"/>
      <size height="16" width="16"/>
      <depth>10</depth>
      <locked>false</locked>
    </tile>
    <tile id="10366202">
      <background>tileMetF</background>
      <backgroundPosition x="48" y="0"/>
      <roomPosition x="304" y="112"/>
      <size height="16" width="16"/>
      <depth>10</depth>
      <locked>false</locked>
    </tile>
    <tile id="10366203">
      <background>tileMetF</background>
      <backgroundPosition x="0" y="16"/>
      <roomPosition x="288" y="176"/>
      <size height="16" width="16"/>
      <depth>10</depth>
      <locked>false</locked>
    </tile>
    <tile id="10366204">
      <background>tileMetF</background>
      <backgroundPosition x="48" y="16"/>
      <roomPosition x="304" y="176"/>
      <size height="16" width="16"/>
      <depth>10</depth>
      <locked>false</locked>
    </tile>
    <tile id="10366205">
      <background>tileMetF</background>
      <backgroundPosition x="96" y="0"/>
      <roomPosition x="272" y="128"/>
      <size height="32" width="16"/>
      <depth>10</depth>
      <locked>false</locked>
    </tile>
    <tile id="10366206">
      <background>tileMetF</background>
      <backgroundPosition x="96" y="48"/>
      <roomPosition x="272" y="160"/>
      <size height="16" width="16"/>
      <depth>10</depth>
      <locked>false</locked>
    </tile>
    <tile id="10366207">
      <background>tileMetF</background>
      <backgroundPosition x="112" y="32"/>
      <roomPosition x="320" y="144"/>
      <size height="32" width="16"/>
      <depth>10</depth>
      <locked>false</locked>
    </tile>
    <tile id="10366208">
      <background>tileMetF</background>
      <backgroundPosition x="112" y="0"/>
      <roomPosition x="320" y="128"/>
      <size height="16" width="16"/>
      <depth>10</depth>
      <locked>false</locked>
    </tile>
    <tile id="10366209">
      <background>tileMetF</background>
      <backgroundPosition x="0" y="144"/>
      <roomPosition x="288" y="128"/>
      <size height="16" width="32"/>
      <depth>10</depth>
      <locked>false</locked>
    </tile>
    <tile id="10366213">
      <background>tileMetF</background>
      <backgroundPosition x="32" y="128"/>
      <roomPosition x="304" y="144"/>
      <size height="32" width="16"/>
      <depth>10</depth>
      <locked>false</locked>
    </tile>
    <tile id="10366214">
      <background>tileMetF</background>
      <backgroundPosition x="32" y="128"/>
      <roomPosition x="288" y="144"/>
      <size height="32" width="16"/>
      <depth>10</depth>
      <locked>false</locked>
    </tile>
    <tile id="10366219">
      <background>tileMetF</background>
      <backgroundPosition x="80" y="16"/>
      <roomPosition x="48" y="240"/>
      <size height="48" width="16"/>
      <depth>10</depth>
      <locked>false</locked>
    </tile>
    <tile id="10366220">
      <background>tileMetF</background>
      <backgroundPosition x="96" y="96"/>
      <roomPosition x="240" y="368"/>
      <size height="16" width="16"/>
      <depth>10</depth>
      <locked>false</locked>
    </tile>
    <tile id="10366221">
      <background>tileMetF</background>
      <backgroundPosition x="80" y="96"/>
      <roomPosition x="352" y="368"/>
      <size height="16" width="16"/>
      <depth>10</depth>
      <locked>false</locked>
    </tile>
    <tile id="10366223">
      <background>tileMetF</background>
      <backgroundPosition x="96" y="0"/>
      <roomPosition x="352" y="384"/>
      <size height="16" width="16"/>
      <depth>10</depth>
      <locked>false</locked>
    </tile>
    <tile id="10366225">
      <background>tileMetF</background>
      <backgroundPosition x="112" y="0"/>
      <roomPosition x="240" y="384"/>
      <size height="16" width="16"/>
      <depth>10</depth>
      <locked>false</locked>
    </tile>
    <tile id="10366227">
      <background>tileMetF</background>
      <backgroundPosition x="112" y="128"/>
      <roomPosition x="240" y="432"/>
      <size height="16" width="16"/>
      <depth>10</depth>
      <locked>false</locked>
    </tile>
    <tile id="10366228">
      <background>tileMetF</background>
      <backgroundPosition x="112" y="128"/>
      <roomPosition x="352" y="432"/>
      <size height="16" width="16"/>
      <depth>10</depth>
      <locked>false</locked>
    </tile>
    <tile id="10366229">
      <background>tileMetF</background>
      <backgroundPosition x="32" y="128"/>
      <roomPosition x="224" y="384"/>
      <size height="32" width="16"/>
      <depth>10</depth>
      <locked>false</locked>
    </tile>
    <tile id="10366230">
      <background>tileMetF</background>
      <backgroundPosition x="32" y="128"/>
      <roomPosition x="224" y="416"/>
      <size height="32" width="16"/>
      <depth>10</depth>
      <locked>false</locked>
    </tile>
    <tile id="10366231">
      <background>tileMetF</background>
      <backgroundPosition x="32" y="128"/>
      <roomPosition x="368" y="384"/>
      <size height="32" width="16"/>
      <depth>10</depth>
      <locked>false</locked>
    </tile>
    <tile id="10366232">
      <background>tileMetF</background>
      <backgroundPosition x="32" y="128"/>
      <roomPosition x="368" y="416"/>
      <size height="32" width="16"/>
      <depth>10</depth>
      <locked>false</locked>
    </tile>
    <tile id="10366237">
      <background>tileMetF</background>
      <backgroundPosition x="80" y="128"/>
      <roomPosition x="0" y="400"/>
      <size height="32" width="32"/>
      <depth>10</depth>
      <locked>false</locked>
    </tile>
    <tile id="10366238">
      <background>tileMetF</background>
      <backgroundPosition x="80" y="128"/>
      <roomPosition x="32" y="400"/>
      <size height="32" width="32"/>
      <depth>10</depth>
      <locked>false</locked>
    </tile>
    <tile id="10366239">
      <background>tileMetF</background>
      <backgroundPosition x="80" y="128"/>
      <roomPosition x="64" y="400"/>
      <size height="32" width="32"/>
      <depth>10</depth>
      <locked>false</locked>
    </tile>
    <tile id="10366240">
      <background>tileMetF</background>
      <backgroundPosition x="80" y="128"/>
      <roomPosition x="96" y="400"/>
      <size height="32" width="32"/>
      <depth>10</depth>
      <locked>false</locked>
    </tile>
    <tile id="10366241">
      <background>tileMetF</background>
      <backgroundPosition x="80" y="128"/>
      <roomPosition x="128" y="400"/>
      <size height="32" width="32"/>
      <depth>10</depth>
      <locked>false</locked>
    </tile>
    <tile id="10366242">
      <background>tileMetF</background>
      <backgroundPosition x="80" y="128"/>
      <roomPosition x="160" y="400"/>
      <size height="32" width="32"/>
      <depth>10</depth>
      <locked>false</locked>
    </tile>
    <tile id="10366243">
      <background>tileMetF</background>
      <backgroundPosition x="80" y="128"/>
      <roomPosition x="192" y="400"/>
      <size height="32" width="32"/>
      <depth>10</depth>
      <locked>false</locked>
    </tile>
    <tile id="10366244">
      <background>tileMetF</background>
      <backgroundPosition x="80" y="128"/>
      <roomPosition x="384" y="400"/>
      <size height="32" width="32"/>
      <depth>10</depth>
      <locked>false</locked>
    </tile>
    <tile id="10366245">
      <background>tileMetF</background>
      <backgroundPosition x="80" y="128"/>
      <roomPosition x="416" y="400"/>
      <size height="32" width="32"/>
      <depth>10</depth>
      <locked>false</locked>
    </tile>
    <tile id="10366246">
      <background>tileMetF</background>
      <backgroundPosition x="80" y="128"/>
      <roomPosition x="448" y="400"/>
      <size height="32" width="32"/>
      <depth>10</depth>
      <locked>false</locked>
    </tile>
    <tile id="10366247">
      <background>tileMetF</background>
      <backgroundPosition x="80" y="128"/>
      <roomPosition x="480" y="400"/>
      <size height="32" width="32"/>
      <depth>10</depth>
      <locked>false</locked>
    </tile>
    <tile id="10366248">
      <background>tileMetF</background>
      <backgroundPosition x="80" y="128"/>
      <roomPosition x="512" y="400"/>
      <size height="32" width="32"/>
      <depth>10</depth>
      <locked>false</locked>
    </tile>
    <tile id="10366249">
      <background>tileMetF</background>
      <backgroundPosition x="80" y="128"/>
      <roomPosition x="544" y="400"/>
      <size height="32" width="32"/>
      <depth>10</depth>
      <locked>false</locked>
    </tile>
    <tile id="10366250">
      <background>tileMetF</background>
      <backgroundPosition x="80" y="128"/>
      <roomPosition x="576" y="400"/>
      <size height="32" width="32"/>
      <depth>10</depth>
      <locked>false</locked>
    </tile>
    <tile id="10366251">
      <background>tileMetF</background>
      <backgroundPosition x="112" y="32"/>
      <roomPosition x="240" y="400"/>
      <size height="32" width="16"/>
      <depth>10</depth>
      <locked>false</locked>
    </tile>
    <tile id="10366252">
      <background>tileMetF</background>
      <backgroundPosition x="96" y="32"/>
      <roomPosition x="352" y="400"/>
      <size height="32" width="16"/>
      <depth>10</depth>
      <locked>false</locked>
    </tile>
  </tiles>
  <editorSettings remember="true">
    <size height="651" width="978"/>
    <showGrid>false</showGrid>
    <showObjects>false</showObjects>
    <showTiles>true</showTiles>
    <showBackgrounds>true</showBackgrounds>
    <showForegrounds>true</showForegrounds>
    <showViews>false</showViews>
    <deleteUnderlyingObjects>true</deleteUnderlyingObjects>
    <deleteUnderlyingTiles>true</deleteUnderlyingTiles>
    <currentTab>0</currentTab>
    <horizontalScrollPosition>-52</horizontalScrollPosition>
    <verticalScrollPosition>-61</verticalScrollPosition>
  </editorSettings>
</room>
